packaway/__init__.py
packaway/version.py
packaway/violation.py
packaway/plugins/__init__.py
packaway/plugins/flake8/__init__.py
packaway/plugins/flake8/import_checker.py
packaway/plugins/flake8/tests/__init__.py
packaway/plugins/flake8/tests/test_import_checker.py
packaway/rules/__init__.py
packaway/rules/_ast_analyzer.py
packaway/rules/regex_rule.py
packaway/rules/underscore_rule.py
packaway/rules/tests/__init__.py
packaway/rules/tests/test_regex_rule.py
packaway/rules/tests/test_underscore_rule.py
packaway-0.3.0.dist-info/LICENSE
packaway-0.3.0.dist-info/METADATA
packaway-0.3.0.dist-info/WHEEL
packaway-0.3.0.dist-info/entry_points.txt
packaway-0.3.0.dist-info/top_level.txt
packaway-0.3.0.dist-info/RECORD
