Metadata-Version: 2.1
Name: packaway
Version: 0.3.0
Summary: Static Checker to Enforce (Some) Encapsulation in Python.
Home-page: https://github.com/kitchoi/packaway
Author: Kit Yan Choi
License: MIT
Platform: UNKNOWN
Classifier: Programming Language :: Python :: 3
Classifier: License :: OSI Approved :: MIT License
Classifier: Operating System :: OS Independent
Requires-Python: >=3.6
License-File: LICENSE
Provides-Extra: test
Requires-Dist: flake8 ; extra == 'test'
